kishimenpy/__init__.py
kishimenpy/api.py
kishimenpy/auth.py
kishimenpy/commands.py
kishimenpy-0.1.1.dist-info/DESCRIPTION.rst
kishimenpy-0.1.1.dist-info/entry_points.txt
kishimenpy-0.1.1.dist-info/METADATA
kishimenpy-0.1.1.dist-info/metadata.json
kishimenpy-0.1.1.dist-info/RECORD
kishimenpy-0.1.1.dist-info/top_level.txt
kishimenpy-0.1.1.dist-info/WHEEL
