Metadata-Version: 2.0
Name: kishimenpy
Version: 0.1.1
Summary: The niconico Downloader
Home-page: https://github.com/drillbits/kishimenpy
Author: Jiro Nejime
Author-email: neji@drillbits.jp
License: MIT
Platform: UNKNOWN
Classifier: Development Status :: 3 - Alpha
Classifier: Intended Audience :: Developers
Classifier: Programming Language :: Python
Classifier: Programming Language :: Python :: 3.4
Classifier: Topic :: Utilities
Classifier: License :: OSI Approved :: MIT License
Requires-Dist: requests
